README
setup.py
oops_celery/__init__.py
oops_celery/oops_reporter.py
oops_celery.egg-info/PKG-INFO
oops_celery.egg-info/SOURCES.txt
oops_celery.egg-info/dependency_links.txt
oops_celery.egg-info/requires.txt
oops_celery.egg-info/top_level.txt
oops_celery/tests/__init__.py
oops_celery/tests/test_integration.py
oops_celery/tests/test_oops_reporter.py