Metadata-Version: 1.0
Name: oops-celery
Version: 0.0.2
Summary: Oops integration for celery
Home-page: http://launchpad.net/python-oops-celery
Author: Launchpad developers
Author-email: launchpad-devs@lists.launchpad.net
License: LGPLv3
Download-URL: https://launchpad.net/python-oops-celery/+download
Platform: UNKNOWN
